Metadata-Version: 2.4
Name: webarenax
Version: 0.3
Summary: This is an unofficial, use-at-your-own risks port of the webarena benchmark, for use as a standalone library package.
License-Expression: Apache-2.0
License-File: LICENSE
Requires-Dist: gymnasium
Requires-Dist: playwright>=1.39
Requires-Dist: Pillow
Requires-Dist: evaluate
Requires-Dist: openai>=1
Requires-Dist: types-tqdm
Requires-Dist: tiktoken
Requires-Dist: aiolimiter
Requires-Dist: beartype>=0.12.0
Requires-Dist: flask
Requires-Dist: nltk
Requires-Dist: text-generation
Requires-Dist: transformers
Dynamic: license-file
